[
    {
        "title": "央视网络春晚",
        "url": "https://www.kuaishou.com/short-video/3xkbrsbsefk68xq",
        "hot_value": "13229000",
        "view_count": null,
        "flag": null,
        "crawl_time": 1737563301
    },
    {
        "title": "国色芳华大结局",
        "url": "https://www.kuaishou.com/short-video/3xjtebq5f79p4m2",
        "hot_value": "12279000",
        "view_count": null,
        "flag": "新",
        "crawl_time": 1737563301
    },
    {
        "title": "新疆家庭网络春晚彩排现场",
        "url": "https://www.kuaishou.com/short-video/3xqhu8vybqd4in4",
        "hot_value": "11581000",
        "view_count": null,
        "flag": null,
        "crawl_time": 1737563301
    },
    {
        "title": "漂白电视剧大结局",
        "url": "https://www.kuaishou.com/short-video/3xjjizwpcds2hi4",
        "hot_value": "10975000",
        "view_count": null,
        "flag": null,
        "crawl_time": 1737563301
    },
    {
        "title": "赵本山小品回忆杀",
        "url": "https://www.kuaishou.com/short-video/3xbchhn443gzkau",
        "hot_value": "10321000",
        "view_count": null,
        "flag": null,
        "crawl_time": 1737563301
    },
    {
        "title": "黄金大涨金价突破830关口",
        "url": "https://www.kuaishou.com/short-video/3xgb8txt3jc34yq",
        "hot_value": "9901000",
        "view_count": null,
        "flag": null,
        "crawl_time": 1737563301
    },
    {
        "title": "17岁网红云豹干干离世",
        "url": "https://www.kuaishou.com/short-video/3xtvntyfnftnegi",
        "hot_value": "9681000",
        "view_count": null,
        "flag": null,
        "crawl_time": 1737563301
    },
    {
        "title": "高考0分有多爽",
        "url": "https://www.kuaishou.com/short-video/3xcf3crpcj8ynmq",
        "hot_value": "9612000",
        "view_count": null,
        "flag": null,
        "crawl_time": 1737563301
    },
    {
        "title": "男子杀害妻子一家三口27年后落网",
        "url": "https://www.kuaishou.com/short-video/3xzzjpq49a3s3iw",
        "hot_value": "9590000",
        "view_count": null,
        "flag": null,
        "crawl_time": 1737563301
    },
    {
        "title": "南方小年",
        "url": "https://www.kuaishou.com/short-video/3xchhud7crw4sjm",
        "hot_value": "9567000",
        "view_count": null,
        "flag": "新",
        "crawl_time": 1737563301
    },
    {
        "title": "专家谈乌军总司令虚报战果",
        "url": "https://www.kuaishou.com/short-video/3xvuk6nubfnftbg",
        "hot_value": "9506000",
        "view_count": null,
        "flag": null,
        "crawl_time": 1737563301
    },
    {
        "title": "官方辟谣郑州一人跳桥被火车撞亡",
        "url": "https://www.kuaishou.com/short-video/3xsuvmhr26ur3i2",
        "hot_value": "9502000",
        "view_count": null,
        "flag": null,
        "crawl_time": 1737563301
    },
    {
        "title": "iPhone17Air背板",
        "url": "https://www.kuaishou.com/short-video/3xmc74zki4mzptu",
        "hot_value": "9444000",
        "view_count": null,
        "flag": null,
        "crawl_time": 1737563301
    },
    {
        "title": "外交部回应中方更改鲁比奥译名",
        "url": "https://www.kuaishou.com/short-video/3x2nn927ikxvbjq",
        "hot_value": "9418000",
        "view_count": null,
        "flag": null,
        "crawl_time": 1737563301
    },
    {
        "title": "安徽春晚定档年二十八",
        "url": "https://www.kuaishou.com/short-video/3xh3mnhs4jsc8xc",
        "hot_value": "9392000",
        "view_count": null,
        "flag": null,
        "crawl_time": 1737563301
    },
    {
        "title": "东北人打扑克音效",
        "url": "https://www.kuaishou.com/short-video/3xy5n2849jyfu7a",
        "hot_value": "9348000",
        "view_count": null,
        "flag": null,
        "crawl_time": 1737563301
    },
    {
        "title": "叮咚鸡",
        "url": "https://www.kuaishou.com/short-video/3xwneb5bizyacxc",
        "hot_value": "9319000",
        "view_count": null,
        "flag": null,
        "crawl_time": 1737563301
    },
    {
        "title": "美国一男子被女警拿枪时走火射中",
        "url": "https://www.kuaishou.com/short-video/3xci4nvsw2dh449",
        "hot_value": "9298000",
        "view_count": null,
        "flag": null,
        "crawl_time": 1737563301
    },
    {
        "title": "我国完成对福岛海水的检测分析",
        "url": "https://www.kuaishou.com/short-video/3xug5s4yqg25zsu",
        "hot_value": "9277000",
        "view_count": null,
        "flag": null,
        "crawl_time": 1737563301
    },
    {
        "title": "小年快乐",
        "url": "https://www.kuaishou.com/short-video/3xberws2twm8nbs",
        "hot_value": "9253000",
        "view_count": null,
        "flag": null,
        "crawl_time": 1737563301
    },
    {
        "title": "贺峻霖青海摇",
        "url": "https://www.kuaishou.com/short-video/3x4zzezpywpb38i",
        "hot_value": "9247000",
        "view_count": null,
        "flag": null,
        "crawl_time": 1737563301
    },
    {
        "title": "妲己cos",
        "url": "https://www.kuaishou.com/short-video/3xny2r3esqdf3zi",
        "hot_value": "9246000",
        "view_count": null,
        "flag": null,
        "crawl_time": 1737563301
    },
    {
        "title": "潘宏道歉文已获近70万点赞",
        "url": "https://www.kuaishou.com/short-video/3x3626sxi7ft4q4",
        "hot_value": "9245000",
        "view_count": null,
        "flag": null,
        "crawl_time": 1737563301
    },
    {
        "title": "专家称尸检有助于确定艾特死因",
        "url": "https://www.kuaishou.com/short-video/3xdmbgkq4fvyxuu",
        "hot_value": "9233000",
        "view_count": null,
        "flag": null,
        "crawl_time": 1737563301
    },
    {
        "title": "潘宏曾有刑事犯罪记录",
        "url": "https://www.kuaishou.com/short-video/3xnw4abpdm2uhwi",
        "hot_value": "9232000",
        "view_count": null,
        "flag": null,
        "crawl_time": 1737563301
    },
    {
        "title": "四首歌就到了东北",
        "url": "https://www.kuaishou.com/short-video/3xbhx5e8n3rhy76",
        "hot_value": "9227000",
        "view_count": null,
        "flag": null,
        "crawl_time": 1737563301
    },
    {
        "title": "樱桃精神状态遥遥领先",
        "url": "https://www.kuaishou.com/short-video/3x7zn6fb3v4wgg9",
        "hot_value": "9205000",
        "view_count": null,
        "flag": null,
        "crawl_time": 1737563301
    },
    {
        "title": "短剧太阳雨开机",
        "url": "https://www.kuaishou.com/short-video/3x3vhrgtvupcsf2",
        "hot_value": "9177000",
        "view_count": null,
        "flag": null,
        "crawl_time": 1737563301
    },
    {
        "title": "呜哇嘡是什么梗",
        "url": "https://www.kuaishou.com/short-video/3xpsxmaibbe7auq",
        "hot_value": "9152000",
        "view_count": null,
        "flag": null,
        "crawl_time": 1737563301
    },
    {
        "title": "在华10年美国人警告中国人",
        "url": "https://www.kuaishou.com/short-video/3xn52cjk9bfnxdk",
        "hot_value": "9145000",
        "view_count": null,
        "flag": null,
        "crawl_time": 1737563301
    },
    {
        "title": "oiiai猫的风吹到了城市广场",
        "url": "https://www.kuaishou.com/short-video/3xzsv8y4egmdm6c",
        "hot_value": "9098000",
        "view_count": null,
        "flag": null,
        "crawl_time": 1737563301
    },
    {
        "title": "马大帅已读乱回",
        "url": "https://www.kuaishou.com/short-video/3xqga43cj8x4dac",
        "hot_value": "9070000",
        "view_count": null,
        "flag": null,
        "crawl_time": 1737563301
    },
    {
        "title": "美国究竟欠了联合国多少钱",
        "url": "https://www.kuaishou.com/short-video/3xydnvpvzddtd84",
        "hot_value": "9058000",
        "view_count": null,
        "flag": null,
        "crawl_time": 1737563301
    },
    {
        "title": "裴擒虎FMVP皮肤优化",
        "url": "https://www.kuaishou.com/short-video/3xche8ptt63bxmy",
        "hot_value": "9016000",
        "view_count": null,
        "flag": "新",
        "crawl_time": 1737563301
    },
    {
        "title": "网络视听盛典全阵容海报发布",
        "url": "https://www.kuaishou.com/short-video/3xrabh63cktiega",
        "hot_value": "8994000",
        "view_count": null,
        "flag": null,
        "crawl_time": 1737563301
    },
    {
        "title": "孙正义带了5000亿",
        "url": "https://www.kuaishou.com/short-video/3xtj3fksdt2e7bc",
        "hot_value": "8972000",
        "view_count": null,
        "flag": null,
        "crawl_time": 1737563301
    },
    {
        "title": "小年文案",
        "url": "https://www.kuaishou.com/short-video/3xpaj6aq7f52zea",
        "hot_value": "8944000",
        "view_count": null,
        "flag": null,
        "crawl_time": 1737563301
    },
    {
        "title": "外国人在线求助数学作业",
        "url": "https://www.kuaishou.com/short-video/3x35rxzufq7iats",
        "hot_value": "8937000",
        "view_count": null,
        "flag": null,
        "crawl_time": 1737563301
    },
    {
        "title": "东方卫视春晚阵容官宣",
        "url": "https://www.kuaishou.com/short-video/3x3jbkapi9wy3xc",
        "hot_value": "8895000",
        "view_count": null,
        "flag": null,
        "crawl_time": 1737563301
    },
    {
        "title": "联合国公开要账",
        "url": "https://www.kuaishou.com/short-video/3x3665gd5fkv3ag",
        "hot_value": "8873000",
        "view_count": null,
        "flag": null,
        "crawl_time": 1737563301
    },
    {
        "title": "apt版二人转",
        "url": "https://www.kuaishou.com/short-video/3xdni9di3umig22",
        "hot_value": "8848000",
        "view_count": null,
        "flag": null,
        "crawl_time": 1737563301
    },
    {
        "title": "乡村爱情搞笑名场面",
        "url": "https://www.kuaishou.com/short-video/3xf8sb6bwd6m2ww",
        "hot_value": "8819000",
        "view_count": null,
        "flag": null,
        "crawl_time": 1737563301
    },
    {
        "title": "郭艾伦半场20分",
        "url": "https://www.kuaishou.com/short-video/3x6nw8ks8my7pbc",
        "hot_value": "8793000",
        "view_count": null,
        "flag": null,
        "crawl_time": 1737563301
    },
    {
        "title": "墨总统回应特朗普将墨西哥湾更名",
        "url": "https://www.kuaishou.com/short-video/3xznxdmyf7qu97a",
        "hot_value": "8779000",
        "view_count": null,
        "flag": null,
        "crawl_time": 1737563301
    },
    {
        "title": "现在的小品为什么不好看了",
        "url": "https://www.kuaishou.com/short-video/3xct8isb3pr8eei",
        "hot_value": "8747000",
        "view_count": null,
        "flag": null,
        "crawl_time": 1737563301
    },
    {
        "title": "东北正宗美食是什么梗",
        "url": "https://www.kuaishou.com/short-video/3xbt9chv27zsbaw",
        "hot_value": "8719000",
        "view_count": null,
        "flag": null,
        "crawl_time": 1737563301
    },
    {
        "title": "国产山猫机器人雪中悍猫行",
        "url": "https://www.kuaishou.com/short-video/3x2rn7vhagq45t2",
        "hot_value": "8689000",
        "view_count": null,
        "flag": "新",
        "crawl_time": 1737563301
    },
    {
        "title": "专家谈特朗普就职百天后或访华",
        "url": "https://www.kuaishou.com/short-video/3x356fjz9p53jic",
        "hot_value": "8688000",
        "view_count": null,
        "flag": null,
        "crawl_time": 1737563301
    },
    {
        "title": "北京男篮大胜深圳男篮",
        "url": "https://www.kuaishou.com/short-video/3xi4939n9cgt45y",
        "hot_value": "8670000",
        "view_count": null,
        "flag": null,
        "crawl_time": 1737563301
    },
    {
        "title": "评论员谈特朗普任期首要任务",
        "url": "https://www.kuaishou.com/short-video/3x3izyx6ud38h99",
        "hot_value": "8663000",
        "view_count": null,
        "flag": null,
        "crawl_time": 1737563301
    }
]