[
    {
        "title": "廖三宁得到14分2板5助",
        "url": "https://so.toutiao.com/search?keyword=%E5%BB%96%E4%B8%89%E5%AE%81%E5%BE%97%E5%88%B014%E5%88%862%E6%9D%BF5%E5%8A%A9&search_json=%7B%22source_aid%22%3A13%7D&source=hotboard_list",
        "flag": "",
        "flag_ext": "",
        "extra": "",
        "crawl_time": 1743031341,
        "view_count": 472652,
        "talk_count": 2028
    },
    {
        "title": "刘玉栋：名人堂是封神榜是玩笑话",
        "url": "https://so.toutiao.com/search?keyword=%E5%88%98%E7%8E%89%E6%A0%8B%EF%BC%9A%E5%90%8D%E4%BA%BA%E5%A0%82%E6%98%AF%E5%B0%81%E7%A5%9E%E6%A6%9C%E6%98%AF%E7%8E%A9%E7%AC%91%E8%AF%9D&search_json=%7B%22source_aid%22%3A13%7D&source=hotboard_list",
        "flag": "",
        "flag_ext": "",
        "extra": "",
        "crawl_time": 1743031341,
        "view_count": 425826,
        "talk_count": 1827
    },
    {
        "title": "名嘴：东契奇是历史级别的球霸",
        "url": "https://so.toutiao.com/search?keyword=%E5%90%8D%E5%98%B4%EF%BC%9A%E4%B8%9C%E5%A5%91%E5%A5%87%E6%98%AF%E5%8E%86%E5%8F%B2%E7%BA%A7%E5%88%AB%E7%9A%84%E7%90%83%E9%9C%B8&search_json=%7B%22source_aid%22%3A13%7D&source=hotboard_list",
        "flag": "",
        "flag_ext": "",
        "extra": "",
        "crawl_time": 1743031341,
        "view_count": 229959,
        "talk_count": 986
    },
    {
        "title": "辽篮115-100轻取北控取6连胜",
        "url": "https://so.toutiao.com/search?keyword=%E8%BE%BD%E7%AF%AE115-100%E8%BD%BB%E5%8F%96%E5%8C%97%E6%8E%A7%E5%8F%966%E8%BF%9E%E8%83%9C&search_json=%7B%22source_aid%22%3A13%7D&source=hotboard_list",
        "flag": "",
        "flag_ext": "",
        "extra": "",
        "crawl_time": 1743031341,
        "view_count": 1796953,
        "talk_count": 7712
    },
    {
        "title": "中国篮球名人堂训练课举行",
        "url": "https://so.toutiao.com/search?keyword=%E4%B8%AD%E5%9B%BD%E7%AF%AE%E7%90%83%E5%90%8D%E4%BA%BA%E5%A0%82%E8%AE%AD%E7%BB%83%E8%AF%BE%E4%B8%BE%E8%A1%8C&search_json=%7B%22source_aid%22%3A13%7D&source=hotboard_list",
        "flag": "",
        "flag_ext": "",
        "extra": "",
        "crawl_time": 1743031341,
        "view_count": 274039,
        "talk_count": 1176
    },
    {
        "title": "丁威迪：必须承认尼克斯是支强队",
        "url": "https://so.toutiao.com/search?keyword=%E4%B8%81%E5%A8%81%E8%BF%AA%EF%BC%9A%E5%BF%85%E9%A1%BB%E6%89%BF%E8%AE%A4%E5%B0%BC%E5%85%8B%E6%96%AF%E6%98%AF%E6%94%AF%E5%BC%BA%E9%98%9F&search_json=%7B%22source_aid%22%3A13%7D&source=hotboard_list",
        "flag": "",
        "flag_ext": "",
        "extra": "",
        "crawl_time": 1743031341,
        "view_count": 38767,
        "talk_count": 166
    },
    {
        "title": "高诗岩14中10砍下27分",
        "url": "https://so.toutiao.com/search?keyword=%E9%AB%98%E8%AF%97%E5%B2%A914%E4%B8%AD10%E7%A0%8D%E4%B8%8B27%E5%88%86&search_json=%7B%22source_aid%22%3A13%7D&source=hotboard_list",
        "flag": "",
        "flag_ext": "",
        "extra": "",
        "crawl_time": 1743031341,
        "view_count": 345362,
        "talk_count": 1482
    },
    {
        "title": "杨鸣：球队化学反应不断提升",
        "url": "https://so.toutiao.com/search?keyword=%E6%9D%A8%E9%B8%A3%EF%BC%9A%E7%90%83%E9%98%9F%E5%8C%96%E5%AD%A6%E5%8F%8D%E5%BA%94%E4%B8%8D%E6%96%AD%E6%8F%90%E5%8D%87&search_json=%7B%22source_aid%22%3A13%7D&source=hotboard_list",
        "flag": "",
        "flag_ext": "",
        "extra": "",
        "crawl_time": 1743031341,
        "view_count": 754402,
        "talk_count": 3237
    },
    {
        "title": "记者：快船需要让祖巴茨多打",
        "url": "https://so.toutiao.com/search?keyword=%E8%AE%B0%E8%80%85%EF%BC%9A%E5%BF%AB%E8%88%B9%E9%9C%80%E8%A6%81%E8%AE%A9%E7%A5%96%E5%B7%B4%E8%8C%A8%E5%A4%9A%E6%89%93&search_json=%7B%22source_aid%22%3A13%7D&source=hotboard_list",
        "flag": "",
        "flag_ext": "",
        "extra": "",
        "crawl_time": 1743031341,
        "view_count": 87852,
        "talk_count": 377
    },
    {
        "title": "海兰德：卢曾只让威少打10分钟",
        "url": "https://so.toutiao.com/search?keyword=%E6%B5%B7%E5%85%B0%E5%BE%B7%EF%BC%9A%E5%8D%A2%E6%9B%BE%E5%8F%AA%E8%AE%A9%E5%A8%81%E5%B0%91%E6%89%9310%E5%88%86%E9%92%9F&search_json=%7B%22source_aid%22%3A13%7D&source=hotboard_list",
        "flag": "",
        "flag_ext": "",
        "extra": "",
        "crawl_time": 1743031341,
        "view_count": 37835,
        "talk_count": 162
    }
]