[
    {
        "title": "金正恩观看在俄朝鲜士兵影片时落泪",
        "url": "https://so.toutiao.com/search?keyword=%E9%87%91%E6%AD%A3%E6%81%A9%E8%A7%82%E7%9C%8B%E5%9C%A8%E4%BF%84%E6%9C%9D%E9%B2%9C%E5%A3%AB%E5%85%B5%E5%BD%B1%E7%89%87%E6%97%B6%E8%90%BD%E6%B3%AA&search_json=%7B%22source_aid%22%3A13%7D&source=hotboard_list",
        "flag": "",
        "flag_ext": "",
        "extra": "",
        "crawl_time": 1751347715,
        "view_count": 1478147,
        "talk_count": 6343
    },
    {
        "title": "专家：印度在中印边境问题上放软姿态",
        "url": "https://so.toutiao.com/search?keyword=%E4%B8%93%E5%AE%B6%EF%BC%9A%E5%8D%B0%E5%BA%A6%E5%9C%A8%E4%B8%AD%E5%8D%B0%E8%BE%B9%E5%A2%83%E9%97%AE%E9%A2%98%E4%B8%8A%E6%94%BE%E8%BD%AF%E5%A7%BF%E6%80%81&search_json=%7B%22source_aid%22%3A13%7D&source=hotboard_list",
        "flag": "",
        "flag_ext": "",
        "extra": "",
        "crawl_time": 1751347715,
        "view_count": 335189,
        "talk_count": 1438
    },
    {
        "title": "计划邀请特朗普参加阅兵？中方回应",
        "url": "https://so.toutiao.com/search?keyword=%E8%AE%A1%E5%88%92%E9%82%80%E8%AF%B7%E7%89%B9%E6%9C%97%E6%99%AE%E5%8F%82%E5%8A%A0%E9%98%85%E5%85%B5%EF%BC%9F%E4%B8%AD%E6%96%B9%E5%9B%9E%E5%BA%94&search_json=%7B%22source_aid%22%3A13%7D&source=hotboard_list",
        "flag": "",
        "flag_ext": "",
        "extra": "",
        "crawl_time": 1751347715,
        "view_count": 36509527,
        "talk_count": 156693
    },
    {
        "title": "美两名前总统罕见发声批评特朗普政府",
        "url": "https://so.toutiao.com/search?keyword=%E7%BE%8E%E4%B8%A4%E5%90%8D%E5%89%8D%E6%80%BB%E7%BB%9F%E7%BD%95%E8%A7%81%E5%8F%91%E5%A3%B0%E6%89%B9%E8%AF%84%E7%89%B9%E6%9C%97%E6%99%AE%E6%94%BF%E5%BA%9C&search_json=%7B%22source_aid%22%3A13%7D&source=hotboard_list",
        "flag": "",
        "flag_ext": "",
        "extra": "",
        "crawl_time": 1751347715,
        "view_count": 557205,
        "talk_count": 2391
    },
    {
        "title": "福克斯主播污蔑中国遭特朗普反问",
        "url": "https://so.toutiao.com/search?keyword=%E7%A6%8F%E5%85%8B%E6%96%AF%E4%B8%BB%E6%92%AD%E6%B1%A1%E8%94%91%E4%B8%AD%E5%9B%BD%E9%81%AD%E7%89%B9%E6%9C%97%E6%99%AE%E5%8F%8D%E9%97%AE&search_json=%7B%22source_aid%22%3A13%7D&source=hotboard_list",
        "flag": "",
        "flag_ext": "",
        "extra": "",
        "crawl_time": 1751347715,
        "view_count": 16593764,
        "talk_count": 71217
    },
    {
        "title": "博主：九三阅兵或成国际格局分水岭",
        "url": "https://so.toutiao.com/search?keyword=%E5%8D%9A%E4%B8%BB%EF%BC%9A%E4%B9%9D%E4%B8%89%E9%98%85%E5%85%B5%E6%88%96%E6%88%90%E5%9B%BD%E9%99%85%E6%A0%BC%E5%B1%80%E5%88%86%E6%B0%B4%E5%B2%AD&search_json=%7B%22source_aid%22%3A13%7D&source=hotboard_list",
        "flag": "",
        "flag_ext": "",
        "extra": "",
        "crawl_time": 1751347715,
        "view_count": 8497303,
        "talk_count": 36469
    },
    {
        "title": "野牛跌入89℃温泉被活活煮死",
        "url": "https://so.toutiao.com/search?keyword=%E9%87%8E%E7%89%9B%E8%B7%8C%E5%85%A589%E2%84%83%E6%B8%A9%E6%B3%89%E8%A2%AB%E6%B4%BB%E6%B4%BB%E7%85%AE%E6%AD%BB&search_json=%7B%22source_aid%22%3A13%7D&source=hotboard_list",
        "flag": "",
        "flag_ext": "",
        "extra": "",
        "crawl_time": 1751347715,
        "view_count": 3875674,
        "talk_count": 16633
    },
    {
        "title": "特朗普对华态度转变有何目的",
        "url": "https://so.toutiao.com/search?keyword=%E7%89%B9%E6%9C%97%E6%99%AE%E5%AF%B9%E5%8D%8E%E6%80%81%E5%BA%A6%E8%BD%AC%E5%8F%98%E6%9C%89%E4%BD%95%E7%9B%AE%E7%9A%84&search_json=%7B%22source_aid%22%3A13%7D&source=hotboard_list",
        "flag": "",
        "flag_ext": "",
        "extra": "",
        "crawl_time": 1751347715,
        "view_count": 12396173,
        "talk_count": 53202
    },
    {
        "title": "特朗普急于访华有何原因",
        "url": "https://so.toutiao.com/search?keyword=%E7%89%B9%E6%9C%97%E6%99%AE%E6%80%A5%E4%BA%8E%E8%AE%BF%E5%8D%8E%E6%9C%89%E4%BD%95%E5%8E%9F%E5%9B%A0&search_json=%7B%22source_aid%22%3A13%7D&source=hotboard_list",
        "flag": "",
        "flag_ext": "",
        "extra": "",
        "crawl_time": 1751347715,
        "view_count": 9206664,
        "talk_count": 39513
    },
    {
        "title": "中美俄元首同框可能性有多大",
        "url": "https://so.toutiao.com/search?keyword=%E4%B8%AD%E7%BE%8E%E4%BF%84%E5%85%83%E9%A6%96%E5%90%8C%E6%A1%86%E5%8F%AF%E8%83%BD%E6%80%A7%E6%9C%89%E5%A4%9A%E5%A4%A7&search_json=%7B%22source_aid%22%3A13%7D&source=hotboard_list",
        "flag": "",
        "flag_ext": "",
        "extra": "",
        "crawl_time": 1751347715,
        "view_count": 2235488,
        "talk_count": 9594
    },
    {
        "title": "如何看待印度向中方提永久划界问题",
        "url": "https://so.toutiao.com/search?keyword=%E5%A6%82%E4%BD%95%E7%9C%8B%E5%BE%85%E5%8D%B0%E5%BA%A6%E5%90%91%E4%B8%AD%E6%96%B9%E6%8F%90%E6%B0%B8%E4%B9%85%E5%88%92%E7%95%8C%E9%97%AE%E9%A2%98&search_json=%7B%22source_aid%22%3A13%7D&source=hotboard_list",
        "flag": "",
        "flag_ext": "",
        "extra": "",
        "crawl_time": 1751347715,
        "view_count": 4296968,
        "talk_count": 18441
    },
    {
        "title": "特朗普目前正在遭遇怎样的危机",
        "url": "https://so.toutiao.com/search?keyword=%E7%89%B9%E6%9C%97%E6%99%AE%E7%9B%AE%E5%89%8D%E6%AD%A3%E5%9C%A8%E9%81%AD%E9%81%87%E6%80%8E%E6%A0%B7%E7%9A%84%E5%8D%B1%E6%9C%BA&search_json=%7B%22source_aid%22%3A13%7D&source=hotboard_list",
        "flag": "",
        "flag_ext": "",
        "extra": "",
        "crawl_time": 1751347715,
        "view_count": 12702187,
        "talk_count": 54515
    },
    {
        "title": "日本为何格外关注特朗普是否会访华",
        "url": "https://so.toutiao.com/search?keyword=%E6%97%A5%E6%9C%AC%E4%B8%BA%E4%BD%95%E6%A0%BC%E5%A4%96%E5%85%B3%E6%B3%A8%E7%89%B9%E6%9C%97%E6%99%AE%E6%98%AF%E5%90%A6%E4%BC%9A%E8%AE%BF%E5%8D%8E&search_json=%7B%22source_aid%22%3A13%7D&source=hotboard_list",
        "flag": "",
        "flag_ext": "",
        "extra": "",
        "crawl_time": 1751347715,
        "view_count": 9060749,
        "talk_count": 38887
    },
    {
        "title": "金正恩携女儿与俄文化部长观看演出",
        "url": "https://so.toutiao.com/search?keyword=%E9%87%91%E6%AD%A3%E6%81%A9%E6%90%BA%E5%A5%B3%E5%84%BF%E4%B8%8E%E4%BF%84%E6%96%87%E5%8C%96%E9%83%A8%E9%95%BF%E8%A7%82%E7%9C%8B%E6%BC%94%E5%87%BA&search_json=%7B%22source_aid%22%3A13%7D&source=hotboard_list",
        "flag": "",
        "flag_ext": "",
        "extra": "",
        "crawl_time": 1751347715,
        "view_count": 3524020,
        "talk_count": 15124
    },
    {
        "title": "专家：尹锡悦政治尊严碎了一地",
        "url": "https://so.toutiao.com/search?keyword=%E4%B8%93%E5%AE%B6%EF%BC%9A%E5%B0%B9%E9%94%A1%E6%82%A6%E6%94%BF%E6%B2%BB%E5%B0%8A%E4%B8%A5%E7%A2%8E%E4%BA%86%E4%B8%80%E5%9C%B0&search_json=%7B%22source_aid%22%3A13%7D&source=hotboard_list",
        "flag": "",
        "flag_ext": "",
        "extra": "",
        "crawl_time": 1751347715,
        "view_count": 2106538,
        "talk_count": 9040
    },
    {
        "title": "若特朗普访华中美将“战略摊牌”吗",
        "url": "https://so.toutiao.com/search?keyword=%E8%8B%A5%E7%89%B9%E6%9C%97%E6%99%AE%E8%AE%BF%E5%8D%8E%E4%B8%AD%E7%BE%8E%E5%B0%86%E2%80%9C%E6%88%98%E7%95%A5%E6%91%8A%E7%89%8C%E2%80%9D%E5%90%97&search_json=%7B%22source_aid%22%3A13%7D&source=hotboard_list",
        "flag": "",
        "flag_ext": "",
        "extra": "",
        "crawl_time": 1751347715,
        "view_count": 28567589,
        "talk_count": 122607
    },
    {
        "title": "中美关系怎样才能达到互不干扰状态",
        "url": "https://so.toutiao.com/search?keyword=%E4%B8%AD%E7%BE%8E%E5%85%B3%E7%B3%BB%E6%80%8E%E6%A0%B7%E6%89%8D%E8%83%BD%E8%BE%BE%E5%88%B0%E4%BA%92%E4%B8%8D%E5%B9%B2%E6%89%B0%E7%8A%B6%E6%80%81&search_json=%7B%22source_aid%22%3A13%7D&source=hotboard_list",
        "flag": "",
        "flag_ext": "forum",
        "extra": "话题",
        "crawl_time": 1751347715,
        "view_count": 53362,
        "talk_count": 229
    },
    {
        "title": "为何印度高铁项目延期要扯到中国",
        "url": "https://so.toutiao.com/search?keyword=%E4%B8%BA%E4%BD%95%E5%8D%B0%E5%BA%A6%E9%AB%98%E9%93%81%E9%A1%B9%E7%9B%AE%E5%BB%B6%E6%9C%9F%E8%A6%81%E6%89%AF%E5%88%B0%E4%B8%AD%E5%9B%BD&search_json=%7B%22source_aid%22%3A13%7D&source=hotboard_list",
        "flag": "",
        "flag_ext": "",
        "extra": "",
        "crawl_time": 1751347715,
        "view_count": 2368287,
        "talk_count": 10164
    },
    {
        "title": "民调暴跌 佩通坦大势已去吗",
        "url": "https://so.toutiao.com/search?keyword=%E6%B0%91%E8%B0%83%E6%9A%B4%E8%B7%8C+%E4%BD%A9%E9%80%9A%E5%9D%A6%E5%A4%A7%E5%8A%BF%E5%B7%B2%E5%8E%BB%E5%90%97&search_json=%7B%22source_aid%22%3A13%7D&source=hotboard_list",
        "flag": "",
        "flag_ext": "",
        "extra": "",
        "crawl_time": 1751347715,
        "view_count": 8653636,
        "talk_count": 37140
    },
    {
        "title": "李在明上台将满月 表现如何",
        "url": "https://so.toutiao.com/search?keyword=%E6%9D%8E%E5%9C%A8%E6%98%8E%E4%B8%8A%E5%8F%B0%E5%B0%86%E6%BB%A1%E6%9C%88+%E8%A1%A8%E7%8E%B0%E5%A6%82%E4%BD%95&search_json=%7B%22source_aid%22%3A13%7D&source=hotboard_list",
        "flag": "",
        "flag_ext": "",
        "extra": "",
        "crawl_time": 1751347715,
        "view_count": 2532354,
        "talk_count": 10868
    }
]