[
    {
        "title": "大V：为什么中国不能没有纯血鸿蒙",
        "url": "https://api.toutiaoapi.com/feoffline/amos_land/new/html/main/index.html?category_name=topic_innerflow&event_type=hot_board&log_pb=%7B%22category_name%22%3A%22news_hotspot%22%2C%22entrance_hotspot%22%3A%22channel%22%2C%22first_group_id%22%3A%227429221487468351003%22%2C%22interest_category%22%3A%22technology%22%2C%22location%22%3A%22hot_board%22%2C%22module_rank%22%3A%224%22%2C%22style_id%22%3A%2210230%22%7D&topic_id=7429221487468351003",
        "flag": "",
        "flag_ext": "",
        "extra": "",
        "crawl_time": 1729808413,
        "view_count": 1987345,
        "talk_count": 8529
    },
    {
        "title": "雷军回应小米15涨价",
        "url": "https://api.toutiaoapi.com/feoffline/amos_land/new/html/main/index.html?category_name=topic_innerflow&event_type=hot_board&log_pb=%7B%22category_name%22%3A%22news_hotspot%22%2C%22entrance_hotspot%22%3A%22channel%22%2C%22first_group_id%22%3A%227429300504678862362%22%2C%22interest_category%22%3A%22technology%22%2C%22location%22%3A%22hot_board%22%2C%22module_rank%22%3A%224%22%2C%22style_id%22%3A%2210230%22%7D&topic_id=7429300504678862362",
        "flag": "",
        "flag_ext": "",
        "extra": "",
        "crawl_time": 1729808413,
        "view_count": 930136,
        "talk_count": 3992
    },
    {
        "title": "特斯拉今年股价已下跌13%",
        "url": "https://api.toutiaoapi.com/feoffline/amos_land/new/html/main/index.html?category_name=topic_innerflow&event_type=hot_board&log_pb=%7B%22category_name%22%3A%22news_hotspot%22%2C%22entrance_hotspot%22%3A%22channel%22%2C%22first_group_id%22%3A%227427850515952959515%22%2C%22interest_category%22%3A%22technology%22%2C%22location%22%3A%22hot_board%22%2C%22module_rank%22%3A%224%22%2C%22style_id%22%3A%2210230%22%7D&topic_id=7427850515952959515",
        "flag": "",
        "flag_ext": "",
        "extra": "",
        "crawl_time": 1729808413,
        "view_count": 462275,
        "talk_count": 1984
    },
    {
        "title": "专家：北斗三号卫星圆满收官",
        "url": "https://api.toutiaoapi.com/feoffline/amos_land/new/html/main/index.html?category_name=topic_innerflow&event_type=hot_board&log_pb=%7B%22category_name%22%3A%22news_hotspot%22%2C%22entrance_hotspot%22%3A%22channel%22%2C%22first_group_id%22%3A%227429303141592023091%22%2C%22interest_category%22%3A%22technology%22%2C%22location%22%3A%22hot_board%22%2C%22module_rank%22%3A%224%22%2C%22style_id%22%3A%2210230%22%7D&topic_id=7429303141592023091",
        "flag": "",
        "flag_ext": "",
        "extra": "",
        "crawl_time": 1729808413,
        "view_count": 204154,
        "talk_count": 876
    },
    {
        "title": "人形机器人在武汉加速走向现实",
        "url": "https://api.toutiaoapi.com/feoffline/amos_land/new/html/main/index.html?category_name=topic_innerflow&event_type=hot_board&log_pb=%7B%22category_name%22%3A%22news_hotspot%22%2C%22entrance_hotspot%22%3A%22channel%22%2C%22first_group_id%22%3A%227428853746342346762%22%2C%22interest_category%22%3A%22technology%22%2C%22location%22%3A%22hot_board%22%2C%22module_rank%22%3A%224%22%2C%22style_id%22%3A%2210230%22%7D&topic_id=7428853746342346762",
        "flag": "",
        "flag_ext": "",
        "extra": "",
        "crawl_time": 1729808413,
        "view_count": 383920,
        "talk_count": 1647
    },
    {
        "title": "科学家称大西洋洋流系统已在崩溃边缘",
        "url": "https://api.toutiaoapi.com/feoffline/amos_land/new/html/main/index.html?category_name=topic_innerflow&event_type=hot_board&log_pb=%7B%22category_name%22%3A%22news_hotspot%22%2C%22entrance_hotspot%22%3A%22channel%22%2C%22first_group_id%22%3A%227428780312584568883%22%2C%22interest_category%22%3A%22technology%22%2C%22location%22%3A%22hot_board%22%2C%22module_rank%22%3A%224%22%2C%22style_id%22%3A%2210230%22%7D&topic_id=7428780312584568883",
        "flag": "",
        "flag_ext": "",
        "extra": "",
        "crawl_time": 1729808413,
        "view_count": 215805,
        "talk_count": 926
    },
    {
        "title": "协创数据：签署AI相关战略合作协议",
        "url": "https://api.toutiaoapi.com/feoffline/amos_land/new/html/main/index.html?category_name=topic_innerflow&event_type=hot_board&log_pb=%7B%22category_name%22%3A%22news_hotspot%22%2C%22entrance_hotspot%22%3A%22channel%22%2C%22first_group_id%22%3A%227429306134344990731%22%2C%22interest_category%22%3A%22technology%22%2C%22location%22%3A%22hot_board%22%2C%22module_rank%22%3A%224%22%2C%22style_id%22%3A%2210230%22%7D&topic_id=7429306134344990731",
        "flag": "",
        "flag_ext": "",
        "extra": "",
        "crawl_time": 1729808413,
        "view_count": 14488,
        "talk_count": 62
    },
    {
        "title": "美国14岁少年因沉迷AI聊天自杀",
        "url": "https://api.toutiaoapi.com/feoffline/amos_land/new/html/main/index.html?category_name=topic_innerflow&event_type=hot_board&log_pb=%7B%22category_name%22%3A%22news_hotspot%22%2C%22entrance_hotspot%22%3A%22channel%22%2C%22first_group_id%22%3A%227428963686244401190%22%2C%22interest_category%22%3A%22technology%22%2C%22location%22%3A%22hot_board%22%2C%22module_rank%22%3A%224%22%2C%22style_id%22%3A%2210230%22%7D&topic_id=7428963686244401190",
        "flag": "",
        "flag_ext": "",
        "extra": "",
        "crawl_time": 1729808413,
        "view_count": 40557,
        "talk_count": 174
    },
    {
        "title": "知名分析师称iPhone 16订单减少",
        "url": "https://api.toutiaoapi.com/feoffline/amos_land/new/html/main/index.html?category_name=topic_innerflow&event_type=hot_board&log_pb=%7B%22category_name%22%3A%22news_hotspot%22%2C%22entrance_hotspot%22%3A%22channel%22%2C%22first_group_id%22%3A%227428042517914009611%22%2C%22interest_category%22%3A%22technology%22%2C%22location%22%3A%22hot_board%22%2C%22module_rank%22%3A%224%22%2C%22style_id%22%3A%2210230%22%7D&topic_id=7428042517914009611",
        "flag": "",
        "flag_ext": "",
        "extra": "",
        "crawl_time": 1729808413,
        "view_count": 72831,
        "talk_count": 312
    },
    {
        "title": "智元灵犀X1人形机器人官宣开源",
        "url": "https://api.toutiaoapi.com/feoffline/amos_land/new/html/main/index.html?category_name=topic_innerflow&event_type=hot_board&log_pb=%7B%22category_name%22%3A%22news_hotspot%22%2C%22entrance_hotspot%22%3A%22channel%22%2C%22first_group_id%22%3A%227429185004545654835%22%2C%22interest_category%22%3A%22technology%22%2C%22location%22%3A%22hot_board%22%2C%22module_rank%22%3A%224%22%2C%22style_id%22%3A%2210230%22%7D&topic_id=7429185004545654835",
        "flag": "",
        "flag_ext": "",
        "extra": "",
        "crawl_time": 1729808413,
        "view_count": 75115,
        "talk_count": 322
    }
]